opticol/__init__.py
opticol/_mapping.py
opticol/_meta.py
opticol/_sentinel.py
opticol/_sequence.py
opticol/_set.py
opticol/factory.py
opticol/projector.py
opticol/py.typed
opticol-0.1.0b1.dist-info/METADATA
opticol-0.1.0b1.dist-info/WHEEL
opticol-0.1.0b1.dist-info/top_level.txt
opticol-0.1.0b1.dist-info/RECORD
