Metadata-Version: 2.4
Name: opticol
Version: 0.1.0b1
Summary: Memory optimized implementations for the main Python Collection ABCs.
Requires-Python: >=3.12
